pythonav-0.1.0a1.dist-info/entry_points.txt
pythonav-0.1.0a1.dist-info/AUTHORS.rst
pythonav-0.1.0a1.dist-info/LICENSE.txt
pythonav-0.1.0a1.dist-info/AUTHORS.py
pythonav-0.1.0a1.dist-info/RECORD
pythonav-0.1.0a1.dist-info/METADATA
pythonav-0.1.0a1.dist-info/top_level.txt
pythonav-0.1.0a1.dist-info/WHEEL
pythonav.libs/libharfbuzz-363addf3.so.0.40100.0
pythonav.libs/libxcb-d804e87a.so.1.1.0
pythonav.libs/libavdevice-eac247ee.so.59.7.100
pythonav.libs/libgmp-a51561f6.so.10.4.1
pythonav.libs/libx265-d22fe0ea.so.199
pythonav.libs/libxcb-xfixes-5edf0b60.so.0.0.0
pythonav.libs/libgnutls-1600b7dc.so.30.31.0
pythonav.libs/libfreetype-eef9777a.so.6.17.1
pythonav.libs/libtheoraenc-d63232bb.so.1.1.2
pythonav.libs/libbluray-8826c5c9.so.2.1.2
pythonav.libs/libxcb-shm-1d91c82b.so.0.0.0
pythonav.libs/libaom-41228dfa.so.3.2.0
pythonav.libs/libvorbisenc-15580d7b.so.2.0.12
pythonav.libs/libxcb-shape-8bb943ca.so.0.0.0
pythonav.libs/libXau-47b7cdfd.so.6.0.0
pythonav.libs/libswscale-dd805576.so.6.7.100
pythonav.libs/libdav1d-f40fe09f.so.5.1.1
pythonav.libs/libopencore-amrnb-7a23e5bb.so.0.0.3
pythonav.libs/libass-d3868387.so.9.1.3
pythonav.libs/libavcodec-c8a8a64a.so.59.37.100
pythonav.libs/libfribidi-4ffb17a6.so.0.4.0
pythonav.libs/libxml2-df9466da.so.2.9.13
pythonav.libs/libpostproc-ef703f1b.so.56.6.100
pythonav.libs/libswresample-c1809d69.so.4.7.100
pythonav.libs/libavfilter-c64dc4c4.so.8.44.100
pythonav.libs/libopus-bcf495b4.so.0.8.0
pythonav.libs/libavformat-a048745d.so.59.27.100
pythonav.libs/libnettle-0d117256.so.8.4
pythonav.libs/libhogweed-dea53104.so.6.4
pythonav.libs/libspeex-733b72e4.so.1.5.1
pythonav.libs/libpng16-0d9f3527.so.16.37.0
pythonav.libs/libopenjp2-ffdd4a69.so.2.4.0
pythonav.libs/libtwolame-c263b853.so.0.0.0
pythonav.libs/libavutil-6a0bb8f0.so.57.28.100
pythonav.libs/libvorbis-84ebf20f.so.0.4.9
pythonav.libs/libmp3lame-1f3ca713.so.0.0.0
pythonav.libs/libopencore-amrwb-85b96a00.so.0.0.3
pythonav.libs/libuuid-0a7b20a1.so.1.3.0
pythonav.libs/libxvidcore-a558d1b8.so.4.3
pythonav.libs/libfontconfig-361341db.so.1.12.0
pythonav.libs/libogg-304b6dcc.so.0.8.5
pythonav.libs/liblzma-93ed45ce.so.5.2.5
pythonav.libs/libtheoradec-1cfc6608.so.1.1.4
pythonav.libs/libx264-71a1852e.so.164
pythonav.libs/libvpx-0b16d29e.so.7.0.0
