Metadata-Version: 2.1
Name: pythonav
Version: 0.1.0a1
Summary: [FORK] Pythonic bindings for FFmpeg's libraries.
Home-page: https://github.com/dot-six/python-av
Author: Hanz
Author-email: hanz@godot.id
License: BSD
Project-URL: Bug Reports, https://github.com/dot-six/python-av/issues
Project-URL: Documentation, https://pyav.org/docs
Project-URL: Feedstock, https://github.com/conda-forge/av-feedstock
Project-URL: Download, https://pypi.org/project/python-av
Platform: UNKNOWN
Classifier: Development Status :: 5 - Production/Stable
Classifier: Intended Audience :: Developers
Classifier: License :: OSI Approved :: BSD License
Classifier: Natural Language :: English
Classifier: Operating System :: MacOS :: MacOS X
Classifier: Operating System :: POSIX
Classifier: Operating System :: Unix
Classifier: Operating System :: Microsoft :: Windows
Classifier: Programming Language :: Cython
Classifier: Programming Language :: Python :: 3.7
Classifier: Programming Language :: Python :: 3.8
Classifier: Programming Language :: Python :: 3.9
Classifier: Programming Language :: Python :: 3.10
Classifier: Programming Language :: Python :: 3.11
Classifier: Topic :: Software Development :: Libraries :: Python Modules
Classifier: Topic :: Multimedia :: Sound/Audio
Classifier: Topic :: Multimedia :: Sound/Audio :: Conversion
Classifier: Topic :: Multimedia :: Video
Classifier: Topic :: Multimedia :: Video :: Conversion
